[{"name":"Loura","email":"Loura","password":"1234","id":"1111111111","logs":[{"action":"borrowed","time":"2024-12-18","isbn":"9780451524935"}],"loans":["9780451524935"],"saved":[],"notifications":[{"type":"Welcome","id":"1111111111","message":"\uD83C\uDF89 Welcome to BookHaven, Loura! We're thrilled to have you join our community of book lovers. Start exploring our vast collection of books today, and enjoy the journey into the world of stories and knowledge. Happy reading! \uD83D\uDCDA","payload":"Loura","timestamp":1734534149941,"read":true},{"type":"Borrow","id":"1111111111","message":"You've just borrowed the book with the ISBN: 9780451524935","payload":"9780451524935","timestamp":1734534155211,"read":true}]},{"name":"Loura Alammour","email":"rrr","password":"1234","id":"1234567890","logs":[{"action":"borrowed","time":"2024-12-18","isbn":"9781503290563"},{"action":"borrowed","time":"2024-12-18","isbn":"9780061120084"},{"action":"borrowed","time":"2024-12-19","isbn":"9781400079988"}],"loans":["9781503290563","9780061120084","9781400079988"],"saved":[],"notifications":[{"type":"Borrow","id":"1234567890","message":"You've just borrowed the book with the ISBN: 9780061120084","payload":"9780061120084","timestamp":1734539813310,"read":true},{"type":"Borrow","id":"1234567890","message":"You've just borrowed the book with the ISBN: 9781400079988","payload":"9781400079988","timestamp":1734613403762,"read":true}]}]